crow/Crow.py
crow/Crow_logo.png
crow/__init__.py
crow/__main__.py
crow/uitabs/PrePull.py
crow/uitabs/Present.py
crow/uitabs/Pull.py
crow/uitabs/__init__.py
crow/utils/ParseXML.py
crow/utils/RequestFiles.py
crow/utils/__init__.py
crow/utils/config.yaml
crow/utils/crow_globals.py
crow/utils/logger.py
crow/utils/popupwindows/__init__.py
crow/utils/popupwindows/cutoff.py
crow/utils/popupwindows/exclude.py
crow/utils/popupwindows/numberofcutoffs.py
crow/utils/popupwindows/shadebyyield.py
test/__init__.py
test/test_Crow.py
test/data/processed_24-well_data_images.csv
test/data/processed_96-well_data.csv
test/data/processed_96-well_data_with_errors.csv
test/data/processed_96-well_data_with_zeros.csv
test/data/processed_too_big.csv
test/data/raw_data_1.xml
test/data/raw_data_2.xml
test/data/raw_data_3.xml
test/data/raw_data_4.xml
test/data/raw_data_5.xml
test/data/raw_data_6.xml
test/data/raw_data_7.xml
test/data/raw_data_8.xml
test/data/raw_data_9.xml
CrowHTE-2.0.3.dist-info/LICENSE
CrowHTE-2.0.3.dist-info/METADATA
CrowHTE-2.0.3.dist-info/WHEEL
CrowHTE-2.0.3.dist-info/entry_points.txt
CrowHTE-2.0.3.dist-info/top_level.txt
CrowHTE-2.0.3.dist-info/RECORD
