Metadata-Version: 2.1
Name: CrowHTE
Version: 2.0.3
Summary: Python GUI to enable High Throughput Experimentation.
Home-page: https://github.com/JacksonBurns/Crow
Author: Jackson Burns
Author-email: jburnsky@udel.edu
License: MIT
Classifier: Programming Language :: Python :: 3
License-File: LICENSE
Requires-Dist: six
Requires-Dist: kiwisolver (>=1.0.1)
Requires-Dist: python-dateutil (>=2.1)
Requires-Dist: cycler (>=0.10)
Requires-Dist: pyparsing (!=2.0.4,!=2.1.2,!=2.1.6,>=2.0.3)
Requires-Dist: pillow
Requires-Dist: matplotlib (>=3.1.3)
Requires-Dist: pyyaml
Requires-Dist: numpy
